code_interpreter/__init__.py
code_interpreter/code_interpreter.py
code_interpreter/py.typed
code_interpreter/adapters/__init__.py
code_interpreter/adapters/code_adapter.py
code_interpreter/adapters/factory.py
code_interpreter/adapters/converter/__init__.py
code_interpreter/adapters/converter/code_execution_converter.py
code_interpreter/models/__init__.py
code_interpreter/models/code.py
code_interpreter/models/code_sync.py
code_interpreter/services/__init__.py
code_interpreter/services/code.py
code_interpreter/sync/__init__.py
code_interpreter/sync/code_interpreter.py
code_interpreter/sync/adapters/__init__.py
code_interpreter/sync/adapters/code_adapter.py
code_interpreter/sync/adapters/factory.py
code_interpreter/sync/services/__init__.py
code_interpreter/sync/services/code.py
opensandbox_code_interpreter-0.1.1.dist-info/METADATA
opensandbox_code_interpreter-0.1.1.dist-info/WHEEL
opensandbox_code_interpreter-0.1.1.dist-info/licenses/LICENSE
opensandbox_code_interpreter-0.1.1.dist-info/RECORD
